promformat/__init__.py
promformat/__main__.py
promformat/ast_nodes.py
promformat/buffer.py
promformat/error.py
promformat/formatter.py
promformat/parser/PromQLLexer.py
promformat/parser/PromQLParser.py
promformat/parser/PromQLParserListener.py
promformat/parser/PromQLParserVisitor.py
promformat/parser/__init__.py
promformat-1.0.2.dist-info/LICENSE
promformat-1.0.2.dist-info/METADATA
promformat-1.0.2.dist-info/WHEEL
promformat-1.0.2.dist-info/entry_points.txt
promformat-1.0.2.dist-info/top_level.txt
promformat-1.0.2.dist-info/RECORD
