Metadata-Version: 2.1
Name: promformat
Version: 1.0.2
License-File: LICENSE
Requires-Dist: antlr4-python3-runtime (>=4.10)
